project/mdr.v
// Memory Data Register 
// Dual input: from memory (Mdatain) or from bus (BusMuxOut)
// Dual output: to memory (Mdataout) and to bus
module mdr(
    input wire clk,
    input wire reset,
    input wire MDRin, //enable sig
    input wire Read, // select input: 1=from memory, 0=from bus
    input wire [31:0] BusMuxOut,  // input from internal bus
    input wire [31:0] Mdatain, // input from memory
    output reg [31:0] MDR_val  // output (goes to both bus and memory)
);

    always @(posedge clk or posedge reset) begin
        if (reset) begin
            MDR_val <= 32'b0;
        end else if (MDRin) begin
            // if Read=1, load from memory, otherwise load from bus
            MDR_val <= Read ? Mdatain : BusMuxOut;
        end
    end

endmodule

project/tb_mdr.v
`timescale 1ns/10ps

// Testbench for MDR (Memory Data Register)
module tb_mdr;
    reg clk;
    reg reset;
    reg MDRin;
    reg Read;
    reg [31:0] BusMuxOut;
    reg [31:0] Mdatain;
    wire [31:0] MDR_val;

    // Instantiate MDR
    mdr mdr_inst (
        .clk(clk),
        .reset(reset),
        .MDRin(MDRin),
        .Read(Read),
        .BusMuxOut(BusMuxOut),
        .Mdatain(Mdatain),
        .MDR_val(MDR_val)
    );

    // Clock generation: 10ns period
    initial clk = 0;
    always #5 clk = ~clk;

    // Test sequence
    initial begin
        $dumpfile("mdr.vcd");
        $dumpvars(0, tb_mdr);
        
        // Initialize signals
        reset = 1;
        MDRin = 0;
        Read = 0;
        BusMuxOut = 32'h00000000;
        Mdatain = 32'h00000000;
        
        // Release reset
        #10 reset = 0;
        
        // Test 1: Load from bus (Read=0)
        #10;
        BusMuxOut = 32'hDEADBEEF;
        Mdatain = 32'h12345678;
        MDRin = 1;
        Read = 0;  // Select bus input
        #10;
        MDRin = 0;
        #10;
        $display("Test 1 - Load from bus:");
        $display("  Expected: 0xDEADBEEF, Got: 0x%h %s", MDR_val, 
                 (MDR_val == 32'hDEADBEEF) ? "PASS" : "FAIL");
        
        // Test 2: Load from memory (Read=1)
        #10;
        BusMuxOut = 32'hAAAAAAAA;
        Mdatain = 32'h87654321;
        MDRin = 1;
        Read = 1;  // Select memory input
        #10;
        MDRin = 0;
        #10;
        $display("Test 2 - Load from memory:");
        $display("  Expected: 0x87654321, Got: 0x%h %s", MDR_val,
                 (MDR_val == 32'h87654321) ? "PASS" : "FAIL");
        
        // Test 3: No load when MDRin=0
        #10;
        BusMuxOut = 32'hFFFFFFFF;
        Mdatain = 32'h11111111;
        MDRin = 0;  // Should not load
        Read = 0;
        #10;
        $display("Test 3 - Hold value (MDRin=0):");
        $display("  Expected: 0x87654321, Got: 0x%h %s", MDR_val,
                 (MDR_val == 32'h87654321) ? "PASS" : "FAIL");
        
        // Test 4: Reset functionality
        #10;
        reset = 1;
        #10;
        reset = 0;
        #10;
        $display("Test 4 - Reset:");
        $display("  Expected: 0x00000000, Got: 0x%h %s", MDR_val,
                 (MDR_val == 32'h00000000) ? "PASS" : "FAIL");
        
        #20;
        $display("\nMDR Tests Complete");
        $finish;
    end

endmodule

project/mdr.vcd
$date
	Mon Feb  2 22:50:13 2026
$end
$version
	Icarus Verilog
$end
$timescale
	10ps
$end
$scope module tb_mdr $end
$var wire 32 ! MDR_val [31:0] $end
$var reg 32 " BusMuxOut [31:0] $end
$var reg 1 # MDRin $end
$var reg 32 $ Mdatain [31:0] $end
$var reg 1 % Read $end
$var reg 1 & clk $end
$var reg 1 ' reset $end
$scope module mdr_inst $end
$var wire 32 ( BusMuxOut [31:0] $end
$var wire 1 # MDRin $end
$var wire 32 ) Mdatain [31:0] $end
$var wire 1 % Read $end
$var wire 1 & clk $end
$var wire 1 ' reset $end
$var reg 32 * MDR_val [31:0] $end
$upscope $end
$upscope $end
$enddefinitions $end
$comment Show the parameter values. $end
$dumpall
$end
#0
$dumpvars
b0 *
b0 )
b0 (
1'
0&
0%
b0 $
0#
b0 "
b0 !
$end
#500
1&
#1000
0&
0'
#1500
1&
#2000
0&
1#
b10010001101000101011001111000 $
b10010001101000101011001111000 )
b11011110101011011011111011101111 "
b11011110101011011011111011101111 (
#2500
b11011110101011011011111011101111 !
b11011110101011011011111011101111 *
1&
#3000
0&
0#
#3500
1&
#4000
0&
#4500
1&
#5000
0&
1%
1#
b10000111011001010100001100100001 $
b10000111011001010100001100100001 )
b10101010101010101010101010101010 "
b10101010101010101010101010101010 (
#5500
b10000111011001010100001100100001 !
b10000111011001010100001100100001 *
1&
#6000
0&
0#
#6500
1&
#7000
0&
#7500
1&
#8000
0&
0%
b10001000100010001000100010001 $
b10001000100010001000100010001 )
b11111111111111111111111111111111 "
b11111111111111111111111111111111 (
#8500
1&
#9000
0&
#9500
1&
#10000
b0 !
b0 *
0&
1'
#10500
1&
#11000
0&
0'
